nasdaq_data_link_mcp_os/__init__.py
nasdaq_data_link_mcp_os/config.py
nasdaq_data_link_mcp_os/server.py
nasdaq_data_link_mcp_os/resources/__init__.py
nasdaq_data_link_mcp_os/resources/common/__init__.py
nasdaq_data_link_mcp_os/resources/common/countries.py
nasdaq_data_link_mcp_os/resources/equities_360/__init__.py
nasdaq_data_link_mcp_os/resources/equities_360/balance_sheet.py
nasdaq_data_link_mcp_os/resources/equities_360/cash_flow.py
nasdaq_data_link_mcp_os/resources/equities_360/corporate_actions.py
nasdaq_data_link_mcp_os/resources/equities_360/fundamental_details.py
nasdaq_data_link_mcp_os/resources/equities_360/fundamentals.py
nasdaq_data_link_mcp_os/resources/equities_360/reference_data.py
nasdaq_data_link_mcp_os/resources/equities_360/statistics.py
nasdaq_data_link_mcp_os/resources/rtat/__init__.py
nasdaq_data_link_mcp_os/resources/rtat/retail_activity.py
nasdaq_data_link_mcp_os/resources/world_data_bank/__init__.py
nasdaq_data_link_mcp_os/resources/world_data_bank/indicators.py
nasdaq_data_link_mcp_os-0.2.0.dist-info/licenses/LICENSE
nasdaq_data_link_mcp_os-0.2.0.dist-info/METADATA
nasdaq_data_link_mcp_os-0.2.0.dist-info/WHEEL
nasdaq_data_link_mcp_os-0.2.0.dist-info/top_level.txt
nasdaq_data_link_mcp_os-0.2.0.dist-info/RECORD
