Metadata-Version: 2.4
Name: nasdaq-data-link-mcp-os
Version: 0.2.0
Summary: Community maintained and open-source MCP server for the Nasdaq Data Link
Author-email: Stefano Amorelli <stefano@amorelli.tech>
License: MIT License
Project-URL: Homepage, https://github.com/stefanoamorelli/nasdaq-data-link-mcp
Project-URL: Bug Tracker, https://github.com/stefanoamorelli/nasdaq-data-link-mcp/issues
Classifier: Programming Language :: Python :: 3
Classifier: License :: OSI Approved :: MIT License
Classifier: Operating System :: OS Independent
Requires-Python: >=3.10
License-File: LICENSE
Requires-Dist: mcp[cli]>=1.6.0
Requires-Dist: nasdaq-data-link
Requires-Dist: pycountry
Dynamic: license-file
